freeplane_tools
