Metadata-Version: 2.1
Name: freeplane-tools
Version: 0.0.14
Summary: This package provides some tooling around translating freeplane mindmap files into other useful formats
Home-page: https://github.com/shollingsworth/freeplane_tools
Author: Steven Hollingsworth
Author-email: hollingsworth.stevend@gmail.com
License: MIT
Project-URL: Changes, https://github.com/shollingsworth/freeplane_tools/blob/main/CHANGELOG.md
Project-URL: Source Code, https://github.com/shollingsworth/freeplane_tools
Project-URL: Issue Tracker, https://github.com/shollingsworth/freeplane_tools/issues/
Project-URL: Twitter, https://twitter.com/_stevo
Project-URL: Documentation, https://shollingsworth.github.io/freeplane_tools/index.html
Keywords: freeplane,mindmap,markdown
Platform: UNKNOWN
Classifier: Development Status :: 5 - Production/Stable
Classifier: Environment :: Console
Classifier: Intended Audience :: Developers
Classifier: License :: OSI Approved :: MIT License
Classifier: Intended Audience :: Education
Classifier: Intended Audience :: End Users/Desktop
Classifier: Intended Audience :: Information Technology
Classifier: Operating System :: OS Independent
Classifier: Programming Language :: Python :: 3 :: Only
Classifier: Programming Language :: Python :: 3.6
Classifier: Programming Language :: Python :: 3.7
Classifier: Programming Language :: Python :: 3.8
Classifier: Programming Language :: Python :: 3.9
Classifier: Topic :: Documentation
Classifier: Topic :: Text Editors :: Documentation
Requires-Python: >=3.6
